{"nm":"manual-gearbox 1","v":"5.9.6","fr":60,"ip":0,"op":59,"w":24,"h":24,"ddd":0,"markers":[],"assets":[{"nm":"manual-gearbox 1","fr":60,"id":"ln4w6oez2e39o1sczo4","layers":[{"ty":3,"ddd":0,"ind":5,"hd":false,"nm":"manual-gearbox 1 - Null","ks":{"a":{"a":0,"k":[0,0]},"o":{"a":0,"k":100},"p":{"a":0,"k":[0,0]},"r":{"a":0,"k":0},"s":{"a":0,"k":[100,100]},"sk":{"a":0,"k":0},"sa":{"a":0,"k":0}},"st":0,"ip":0,"op":60,"bm":0,"sr":1},{"ty":3,"ddd":0,"ind":6,"hd":false,"nm":".vector - Null","parent":5,"ks":{"a":{"a":0,"k":[0,0]},"o":{"a":0,"k":100},"p":{"a":0,"k":[5,8]},"r":{"a":0,"k":0},"s":{"a":0,"k":[100,100]},"sk":{"a":0,"k":0},"sa":{"a":0,"k":0}},"st":0,"ip":0,"op":60,"bm":0,"sr":1,"cl":"vector"},{"ddd":0,"ind":7,"hd":false,"nm":".vector - Stroke","parent":6,"ks":{"a":{"a":0,"k":[0,0]},"p":{"a":0,"k":[0,0]},"s":{"a":0,"k":[100,100]},"sk":{"a":0,"k":0},"sa":{"a":0,"k":0},"r":{"a":0,"k":0},"o":{"a":0,"k":100}},"st":0,"ip":0,"op":60,"bm":0,"sr":1,"cl":"vector","ty":4,"shapes":[{"ty":"gr","nm":"Group","hd":false,"np":3,"it":[{"ty":"sh","nm":"Path","hd":false,"ks":{"a":0,"k":{"c":false,"v":[[14,0],[14,2],[13.4142,3.4142],[12,4],[0,4]],"i":[[0,0],[0,0],[0.3751,-0.3751],[0.5304,0],[0,0]],"o":[[0,0],[0,0.53043],[-0.3750699999999991,0.37507],[0,0],[0,0]]}}},{"ty":"st","o":{"a":0,"k":100},"w":{"a":0,"k":1.5},"c":{"a":0,"k":[0,0,0,1]},"ml":4,"lc":2,"lj":2,"nm":"Stroke","hd":false},{"ty":"tr","a":{"a":0,"k":[0,0]},"p":{"a":0,"k":[0,0]},"s":{"a":0,"k":[100,100]},"sk":{"a":0,"k":0},"sa":{"a":0,"k":0},"r":{"a":0,"k":0},"o":{"a":0,"k":100}}]},{"ty":"gr","nm":"Group","hd":false,"np":3,"it":[{"ty":"rc","nm":"Rectangle","hd":false,"p":{"a":0,"k":[7.75,2.75]},"s":{"a":0,"k":[31,11]},"r":{"a":0,"k":0}},{"ty":"fl","o":{"a":0,"k":0},"c":{"a":0,"k":[0,1,0,1]},"nm":"Fill","hd":false,"r":1},{"ty":"tr","a":{"a":0,"k":[0,0]},"p":{"a":0,"k":[0,0]},"s":{"a":0,"k":[100,100]},"sk":{"a":0,"k":0},"sa":{"a":0,"k":0},"r":{"a":0,"k":0},"o":{"a":0,"k":100}}]}]},{"ty":3,"ddd":0,"ind":8,"hd":false,"nm":".vector - Null","parent":5,"ks":{"a":{"a":0,"k":[0,4]},"o":{"a":0,"k":100},"p":{"a":0,"k":[12,12]},"r":{"a":0,"k":0},"s":{"a":0,"k":[100,100]},"sk":{"a":0,"k":0},"sa":{"a":0,"k":0}},"st":0,"ip":0,"op":60,"bm":0,"sr":1,"cl":"vector"},{"ddd":0,"ind":9,"hd":false,"nm":".vector - Stroke","parent":8,"ks":{"a":{"a":0,"k":[0,0]},"p":{"a":0,"k":[0,0]},"s":{"a":0,"k":[100,100]},"sk":{"a":0,"k":0},"sa":{"a":0,"k":0},"r":{"a":0,"k":0},"o":{"a":0,"k":100}},"st":0,"ip":0,"op":60,"bm":0,"sr":1,"cl":"vector","ty":4,"shapes":[{"ty":"gr","nm":"Group","hd":false,"np":3,"it":[{"ty":"sh","nm":"Path","hd":false,"ks":{"a":1,"k":[{"t":0,"s":[{"c":false,"v":[[0,0],[0,8]],"i":[[0,0],[0,0]],"o":[[0,0],[0,0]]}],"o":{"x":[0.5],"y":[0.35]},"i":{"x":[0.15],"y":[1]}},{"t":8.4,"s":[{"c":false,"v":[[0,1.885],[0,6.115]],"i":[[0,0],[0,0]],"o":[[0,0],[0,0]]}],"o":{"x":[0.5],"y":[0.35]},"i":{"x":[0.15],"y":[1]}},{"t":16.8,"s":[{"c":false,"v":[[0,4],[0,4]],"i":[[0,0],[0,0]],"o":[[0,0],[0,0]]}],"o":{"x":[0.5],"y":[0.35]},"i":{"x":[0.15],"y":[1]}},{"t":60,"s":[{"c":false,"v":[[0,0],[0,8]],"i":[[0,0],[0,0]],"o":[[0,0],[0,0]]}]}]}},{"ty":"st","o":{"a":0,"k":100},"w":{"a":0,"k":1.5},"c":{"a":0,"k":[0,0,0,1]},"ml":4,"lc":2,"lj":2,"nm":"Stroke","hd":false},{"ty":"tr","a":{"a":0,"k":[0,0]},"p":{"a":0,"k":[0,0]},"s":{"a":0,"k":[100,100]},"sk":{"a":0,"k":0},"sa":{"a":0,"k":0},"r":{"a":0,"k":0},"o":{"a":0,"k":100}}]},{"ty":"gr","nm":"Group","hd":false,"np":3,"it":[{"ty":"rc","nm":"Rectangle","hd":false,"p":{"a":0,"k":[0.75,4.75]},"s":{"a":0,"k":[3,19]},"r":{"a":0,"k":0}},{"ty":"fl","o":{"a":0,"k":0},"c":{"a":0,"k":[0,1,0,1]},"nm":"Fill","hd":false,"r":1},{"ty":"tr","a":{"a":0,"k":[0,0]},"p":{"a":0,"k":[0,0]},"s":{"a":0,"k":[100,100]},"sk":{"a":0,"k":0},"sa":{"a":0,"k":0},"r":{"a":0,"k":0},"o":{"a":0,"k":100}}]}]},{"ty":3,"ddd":0,"ind":10,"hd":false,"nm":".vector - Null","parent":5,"ks":{"a":{"a":0,"k":[0,4]},"o":{"a":0,"k":100},"p":{"a":0,"k":[5,12]},"r":{"a":0,"k":0},"s":{"a":0,"k":[100,100]},"sk":{"a":0,"k":0},"sa":{"a":0,"k":0}},"st":0,"ip":0,"op":60,"bm":0,"sr":1,"cl":"vector"},{"ddd":0,"ind":11,"hd":false,"nm":".vector - Stroke","parent":10,"ks":{"a":{"a":0,"k":[0,0]},"p":{"a":0,"k":[0,0]},"s":{"a":0,"k":[100,100]},"sk":{"a":0,"k":0},"sa":{"a":0,"k":0},"r":{"a":0,"k":0},"o":{"a":0,"k":100}},"st":0,"ip":0,"op":60,"bm":0,"sr":1,"cl":"vector","ty":4,"shapes":[{"ty":"gr","nm":"Group","hd":false,"np":3,"it":[{"ty":"sh","nm":"Path","hd":false,"ks":{"a":1,"k":[{"t":0,"s":[{"c":false,"v":[[0,0],[0,8]],"i":[[0,0],[0,0]],"o":[[0,0],[0,0]]}],"o":{"x":[0.5],"y":[0.35]},"i":{"x":[0.15],"y":[1]}},{"t":4.8,"s":[{"c":false,"v":[[0,1.8863],[0,6.1137]],"i":[[0,0],[0,0]],"o":[[0,0],[0,0]]}],"o":{"x":[0.5],"y":[0.35]},"i":{"x":[0.15],"y":[1]}},{"t":9.6,"s":[{"c":false,"v":[[0,4],[0,4]],"i":[[0,0],[0,0]],"o":[[0,0],[0,0]]}],"o":{"x":[0.5],"y":[0.35]},"i":{"x":[0.15],"y":[1]}},{"t":30,"s":[{"c":false,"v":[[0,0],[0,8]],"i":[[0,0],[0,0]],"o":[[0,0],[0,0]]}]}]}},{"ty":"st","o":{"a":0,"k":100},"w":{"a":0,"k":1.5},"c":{"a":0,"k":[0,0,0,1]},"ml":4,"lc":2,"lj":2,"nm":"Stroke","hd":false},{"ty":"tr","a":{"a":0,"k":[0,0]},"p":{"a":0,"k":[0,0]},"s":{"a":0,"k":[100,100]},"sk":{"a":0,"k":0},"sa":{"a":0,"k":0},"r":{"a":0,"k":0},"o":{"a":0,"k":100}}]},{"ty":"gr","nm":"Group","hd":false,"np":3,"it":[{"ty":"rc","nm":"Rectangle","hd":false,"p":{"a":0,"k":[0.75,4.75]},"s":{"a":0,"k":[3,19]},"r":{"a":0,"k":0}},{"ty":"fl","o":{"a":0,"k":0},"c":{"a":0,"k":[0,1,0,1]},"nm":"Fill","hd":false,"r":1},{"ty":"tr","a":{"a":0,"k":[0,0]},"p":{"a":0,"k":[0,0]},"s":{"a":0,"k":[100,100]},"sk":{"a":0,"k":0},"sa":{"a":0,"k":0},"r":{"a":0,"k":0},"o":{"a":0,"k":100}}]}]},{"ty":3,"ddd":0,"ind":12,"hd":false,"nm":".vector - Null","parent":5,"ks":{"a":{"a":0,"k":[2,2]},"o":{"a":1,"k":[{"t":15.600000000000001,"s":[100],"o":{"x":[0.5],"y":[0.35]},"i":{"x":[0.15],"y":[1]}},{"t":19.2,"s":[0],"o":{"x":[0.5],"y":[0.35]},"i":{"x":[0.15],"y":[1]}},{"t":22.8,"s":[100]}]},"p":{"a":1,"k":[{"t":0,"s":[12,18],"o":{"x":[0.5],"y":[0.35]},"i":{"x":[0.15],"y":[1]},"ti":[0,0],"to":[0,0]},{"t":60,"s":[12,6]}]},"r":{"a":0,"k":0},"s":{"a":0,"k":[100,100]},"sk":{"a":0,"k":0},"sa":{"a":0,"k":0}},"st":0,"ip":0,"op":60,"bm":0,"sr":1,"cl":"vector"},{"ddd":0,"ind":13,"hd":false,"nm":".vector - Stroke","parent":12,"ks":{"a":{"a":0,"k":[0,0]},"p":{"a":0,"k":[0,0]},"s":{"a":0,"k":[100,100]},"sk":{"a":0,"k":0},"sa":{"a":0,"k":0},"r":{"a":0,"k":0},"o":{"a":1,"k":[{"t":15.600000000000001,"s":[100],"o":{"x":[0.5],"y":[0.35]},"i":{"x":[0.15],"y":[1]}},{"t":19.2,"s":[0],"o":{"x":[0.5],"y":[0.35]},"i":{"x":[0.15],"y":[1]}},{"t":22.8,"s":[100]}]}},"st":0,"ip":0,"op":60,"bm":0,"sr":1,"cl":"vector","ty":4,"shapes":[{"ty":"gr","nm":"Group","hd":false,"np":3,"it":[{"ty":"sh","nm":"Path","hd":false,"ks":{"a":0,"k":{"c":true,"v":[[0,2],[0.5858,3.4142],[2,4],[3.4142,3.4142],[4,2],[3.4142,0.5858],[2,0],[0.5858,0.5858],[0,2],[0,2]],"i":[[0,0],[-0.3751,-0.3751],[-0.5304,0],[-0.3751,0.3751],[0,0.5304],[0.3751,0.3751],[0.5304,0],[0.3751,-0.3751],[0,-0.5304],[0,0]],"o":[[0,0.53043],[0.37507,0.37507],[0.53043,0],[0.37507,-0.37507],[0,-0.53043],[-0.37507,-0.37507],[-0.53043,0],[-0.37507,0.37507],[0,0],[0,0]]}}},{"ty":"st","o":{"a":0,"k":100},"w":{"a":0,"k":1.5},"c":{"a":0,"k":[0,0,0,1]},"ml":4,"lc":2,"lj":2,"nm":"Stroke","hd":false},{"ty":"tr","a":{"a":0,"k":[0,0]},"p":{"a":0,"k":[0,0]},"s":{"a":0,"k":[100,100]},"sk":{"a":0,"k":0},"sa":{"a":0,"k":0},"r":{"a":0,"k":0},"o":{"a":0,"k":100}}]},{"ty":"gr","nm":"Group","hd":false,"np":3,"it":[{"ty":"rc","nm":"Rectangle","hd":false,"p":{"a":0,"k":[2.75,2.75]},"s":{"a":0,"k":[11,11]},"r":{"a":0,"k":0}},{"ty":"fl","o":{"a":0,"k":0},"c":{"a":0,"k":[0,1,0,1]},"nm":"Fill","hd":false,"r":1},{"ty":"tr","a":{"a":0,"k":[0,0]},"p":{"a":0,"k":[0,0]},"s":{"a":0,"k":[100,100]},"sk":{"a":0,"k":0},"sa":{"a":0,"k":0},"r":{"a":0,"k":0},"o":{"a":0,"k":100}}]}]},{"ty":3,"ddd":0,"ind":14,"hd":false,"nm":".vector - Null","parent":5,"ks":{"a":{"a":0,"k":[2,2]},"o":{"a":1,"k":[{"t":5.3999999999999995,"s":[100.47999999999999],"o":{"x":[0.5],"y":[0.35]},"i":{"x":[0.15],"y":[1]}},{"t":9,"s":[0],"o":{"x":[0.5],"y":[0.35]},"i":{"x":[0.15],"y":[1]}},{"t":12.6,"s":[99.96000000000001]}]},"p":{"a":1,"k":[{"t":0,"s":[5,18],"o":{"x":[0.5],"y":[0.35]},"i":{"x":[0.15],"y":[1]},"ti":[0,0],"to":[0,0]},{"t":30,"s":[5,6]}]},"r":{"a":0,"k":0},"s":{"a":0,"k":[100,100]},"sk":{"a":0,"k":0},"sa":{"a":0,"k":0}},"st":0,"ip":0,"op":60,"bm":0,"sr":1,"cl":"vector"},{"ddd":0,"ind":15,"hd":false,"nm":".vector - Stroke","parent":14,"ks":{"a":{"a":0,"k":[0,0]},"p":{"a":0,"k":[0,0]},"s":{"a":0,"k":[100,100]},"sk":{"a":0,"k":0},"sa":{"a":0,"k":0},"r":{"a":0,"k":0},"o":{"a":1,"k":[{"t":5.3999999999999995,"s":[100.47999999999999],"o":{"x":[0.5],"y":[0.35]},"i":{"x":[0.15],"y":[1]}},{"t":9,"s":[0],"o":{"x":[0.5],"y":[0.35]},"i":{"x":[0.15],"y":[1]}},{"t":12.6,"s":[99.96000000000001]}]}},"st":0,"ip":0,"op":60,"bm":0,"sr":1,"cl":"vector","ty":4,"shapes":[{"ty":"gr","nm":"Group","hd":false,"np":3,"it":[{"ty":"sh","nm":"Path","hd":false,"ks":{"a":0,"k":{"c":true,"v":[[0,2],[0.5858,3.4142],[2,4],[3.4142,3.4142],[4,2],[3.4142,0.5858],[2,0],[0.5858,0.5858],[0,2],[0,2]],"i":[[0,0],[-0.3751,-0.3751],[-0.5304,0],[-0.3751,0.3751],[0,0.5304],[0.3751,0.3751],[0.5304,0],[0.3751,-0.3751],[0,-0.5304],[0,0]],"o":[[0,0.53043],[0.37507,0.37507],[0.53043,0],[0.37507,-0.37507],[0,-0.53043],[-0.37507,-0.37507],[-0.53043,0],[-0.37507,0.37507],[0,0],[0,0]]}}},{"ty":"st","o":{"a":0,"k":100},"w":{"a":0,"k":1.5},"c":{"a":0,"k":[0,0,0,1]},"ml":4,"lc":2,"lj":2,"nm":"Stroke","hd":false},{"ty":"tr","a":{"a":0,"k":[0,0]},"p":{"a":0,"k":[0,0]},"s":{"a":0,"k":[100,100]},"sk":{"a":0,"k":0},"sa":{"a":0,"k":0},"r":{"a":0,"k":0},"o":{"a":0,"k":100}}]},{"ty":"gr","nm":"Group","hd":false,"np":3,"it":[{"ty":"rc","nm":"Rectangle","hd":false,"p":{"a":0,"k":[2.75,2.75]},"s":{"a":0,"k":[11,11]},"r":{"a":0,"k":0}},{"ty":"fl","o":{"a":0,"k":0},"c":{"a":0,"k":[0,1,0,1]},"nm":"Fill","hd":false,"r":1},{"ty":"tr","a":{"a":0,"k":[0,0]},"p":{"a":0,"k":[0,0]},"s":{"a":0,"k":[100,100]},"sk":{"a":0,"k":0},"sa":{"a":0,"k":0},"r":{"a":0,"k":0},"o":{"a":0,"k":100}}]}]},{"ty":3,"ddd":0,"ind":16,"hd":false,"nm":".vector - Null","parent":5,"ks":{"a":{"a":0,"k":[0,0]},"o":{"a":0,"k":100},"p":{"a":0,"k":[17,4]},"r":{"a":0,"k":0},"s":{"a":0,"k":[100,100]},"sk":{"a":0,"k":0},"sa":{"a":0,"k":0}},"st":0,"ip":0,"op":60,"bm":0,"sr":1,"cl":"vector"},{"ddd":0,"ind":17,"hd":false,"nm":".vector - Stroke","parent":16,"ks":{"a":{"a":0,"k":[0,0]},"p":{"a":0,"k":[0,0]},"s":{"a":0,"k":[100,100]},"sk":{"a":0,"k":0},"sa":{"a":0,"k":0},"r":{"a":0,"k":0},"o":{"a":0,"k":100}},"st":0,"ip":0,"op":60,"bm":0,"sr":1,"cl":"vector","ty":4,"shapes":[{"ty":"gr","nm":"Group","hd":false,"np":3,"it":[{"ty":"sh","nm":"Path","hd":false,"ks":{"a":0,"k":{"c":true,"v":[[0,2],[0.5858,3.4142],[2,4],[3.4142,3.4142],[4,2],[3.4142,0.5858],[2,0],[0.5858,0.5858],[0,2],[0,2]],"i":[[0,0],[-0.3751,-0.3751],[-0.5304,0],[-0.3751,0.3751],[0,0.5304],[0.3751,0.3751],[0.5304,0],[0.3751,-0.3751],[0,-0.5304],[0,0]],"o":[[0,0.53043],[0.37507,0.37507],[0.53043,0],[0.37507,-0.37507],[0,-0.53043],[-0.37507,-0.37507],[-0.53043,0],[-0.37507,0.37507],[0,0],[0,0]]}}},{"ty":"st","o":{"a":0,"k":100},"w":{"a":0,"k":1.5},"c":{"a":0,"k":[0,0,0,1]},"ml":4,"lc":2,"lj":2,"nm":"Stroke","hd":false},{"ty":"tr","a":{"a":0,"k":[0,0]},"p":{"a":0,"k":[0,0]},"s":{"a":0,"k":[100,100]},"sk":{"a":0,"k":0},"sa":{"a":0,"k":0},"r":{"a":0,"k":0},"o":{"a":0,"k":100}}]},{"ty":"gr","nm":"Group","hd":false,"np":3,"it":[{"ty":"rc","nm":"Rectangle","hd":false,"p":{"a":0,"k":[2.75,2.75]},"s":{"a":0,"k":[11,11]},"r":{"a":0,"k":0}},{"ty":"fl","o":{"a":0,"k":0},"c":{"a":0,"k":[0,1,0,1]},"nm":"Fill","hd":false,"r":1},{"ty":"tr","a":{"a":0,"k":[0,0]},"p":{"a":0,"k":[0,0]},"s":{"a":0,"k":[100,100]},"sk":{"a":0,"k":0},"sa":{"a":0,"k":0},"r":{"a":0,"k":0},"o":{"a":0,"k":100}}]}]},{"ty":3,"ddd":0,"ind":18,"hd":false,"nm":".vector - Null","parent":5,"ks":{"a":{"a":0,"k":[2,2]},"o":{"a":1,"k":[{"t":15.600000000000001,"s":[100],"o":{"x":[0.5],"y":[0.35]},"i":{"x":[0.15],"y":[1]}},{"t":19.2,"s":[0],"o":{"x":[0.5],"y":[0.35]},"i":{"x":[0.15],"y":[1]}},{"t":22.8,"s":[100]}]},"p":{"a":1,"k":[{"t":0,"s":[12,6],"o":{"x":[0.5],"y":[0.35]},"i":{"x":[0.15],"y":[1]},"ti":[0,0],"to":[0,0]},{"t":60,"s":[12,18]}]},"r":{"a":0,"k":0},"s":{"a":0,"k":[100,100]},"sk":{"a":0,"k":0},"sa":{"a":0,"k":0}},"st":0,"ip":0,"op":60,"bm":0,"sr":1,"cl":"vector"},{"ddd":0,"ind":19,"hd":false,"nm":".vector - Stroke","parent":18,"ks":{"a":{"a":0,"k":[0,0]},"p":{"a":0,"k":[0,0]},"s":{"a":0,"k":[100,100]},"sk":{"a":0,"k":0},"sa":{"a":0,"k":0},"r":{"a":0,"k":0},"o":{"a":1,"k":[{"t":15.600000000000001,"s":[100],"o":{"x":[0.5],"y":[0.35]},"i":{"x":[0.15],"y":[1]}},{"t":19.2,"s":[0],"o":{"x":[0.5],"y":[0.35]},"i":{"x":[0.15],"y":[1]}},{"t":22.8,"s":[100]}]}},"st":0,"ip":0,"op":60,"bm":0,"sr":1,"cl":"vector","ty":4,"shapes":[{"ty":"gr","nm":"Group","hd":false,"np":3,"it":[{"ty":"sh","nm":"Path","hd":false,"ks":{"a":0,"k":{"c":true,"v":[[0,2],[0.5858,3.4142],[2,4],[3.4142,3.4142],[4,2],[3.4142,0.5858],[2,0],[0.5858,0.5858],[0,2],[0,2]],"i":[[0,0],[-0.3751,-0.3751],[-0.5304,0],[-0.3751,0.3751],[0,0.5304],[0.3751,0.3751],[0.5304,0],[0.3751,-0.3751],[0,-0.5304],[0,0]],"o":[[0,0.53043],[0.37507,0.37507],[0.53043,0],[0.37507,-0.37507],[0,-0.53043],[-0.37507,-0.37507],[-0.53043,0],[-0.37507,0.37507],[0,0],[0,0]]}}},{"ty":"st","o":{"a":0,"k":100},"w":{"a":0,"k":1.5},"c":{"a":0,"k":[0,0,0,1]},"ml":4,"lc":2,"lj":2,"nm":"Stroke","hd":false},{"ty":"tr","a":{"a":0,"k":[0,0]},"p":{"a":0,"k":[0,0]},"s":{"a":0,"k":[100,100]},"sk":{"a":0,"k":0},"sa":{"a":0,"k":0},"r":{"a":0,"k":0},"o":{"a":0,"k":100}}]},{"ty":"gr","nm":"Group","hd":false,"np":3,"it":[{"ty":"rc","nm":"Rectangle","hd":false,"p":{"a":0,"k":[2.75,2.75]},"s":{"a":0,"k":[11,11]},"r":{"a":0,"k":0}},{"ty":"fl","o":{"a":0,"k":0},"c":{"a":0,"k":[0,1,0,1]},"nm":"Fill","hd":false,"r":1},{"ty":"tr","a":{"a":0,"k":[0,0]},"p":{"a":0,"k":[0,0]},"s":{"a":0,"k":[100,100]},"sk":{"a":0,"k":0},"sa":{"a":0,"k":0},"r":{"a":0,"k":0},"o":{"a":0,"k":100}}]}]},{"ty":3,"ddd":0,"ind":20,"hd":false,"nm":".vector - Null","parent":5,"ks":{"a":{"a":0,"k":[2,2]},"o":{"a":1,"k":[{"t":5.3999999999999995,"s":[100],"o":{"x":[0.5],"y":[0.35]},"i":{"x":[0.15],"y":[1]}},{"t":9,"s":[0],"o":{"x":[0.5],"y":[0.35]},"i":{"x":[0.15],"y":[1]}},{"t":12.6,"s":[100]}]},"p":{"a":1,"k":[{"t":0,"s":[5,6],"o":{"x":[0.5],"y":[0.35]},"i":{"x":[0.15],"y":[1]},"ti":[0,0],"to":[0,0]},{"t":30,"s":[5,18]}]},"r":{"a":0,"k":0},"s":{"a":0,"k":[100,100]},"sk":{"a":0,"k":0},"sa":{"a":0,"k":0}},"st":0,"ip":0,"op":60,"bm":0,"sr":1,"cl":"vector"},{"ddd":0,"ind":21,"hd":false,"nm":".vector - Stroke","parent":20,"ks":{"a":{"a":0,"k":[0,0]},"p":{"a":0,"k":[0,0]},"s":{"a":0,"k":[100,100]},"sk":{"a":0,"k":0},"sa":{"a":0,"k":0},"r":{"a":0,"k":0},"o":{"a":1,"k":[{"t":5.3999999999999995,"s":[100],"o":{"x":[0.5],"y":[0.35]},"i":{"x":[0.15],"y":[1]}},{"t":9,"s":[0],"o":{"x":[0.5],"y":[0.35]},"i":{"x":[0.15],"y":[1]}},{"t":12.6,"s":[100]}]}},"st":0,"ip":0,"op":60,"bm":0,"sr":1,"cl":"vector","ty":4,"shapes":[{"ty":"gr","nm":"Group","hd":false,"np":3,"it":[{"ty":"sh","nm":"Path","hd":false,"ks":{"a":0,"k":{"c":true,"v":[[0,2],[0.5858,3.4142],[2,4],[3.4142,3.4142],[4,2],[3.4142,0.5858],[2,0],[0.5858,0.5858],[0,2],[0,2]],"i":[[0,0],[-0.3751,-0.3751],[-0.5304,0],[-0.3751,0.3751],[0,0.5304],[0.3751,0.3751],[0.5304,0],[0.3751,-0.3751],[0,-0.5304],[0,0]],"o":[[0,0.53043],[0.37507,0.37507],[0.53043,0],[0.37507,-0.37507],[0,-0.53043],[-0.37507,-0.37507],[-0.53043,0],[-0.37507,0.37507],[0,0],[0,0]]}}},{"ty":"st","o":{"a":0,"k":100},"w":{"a":0,"k":1.5},"c":{"a":0,"k":[0,0,0,1]},"ml":4,"lc":2,"lj":2,"nm":"Stroke","hd":false},{"ty":"tr","a":{"a":0,"k":[0,0]},"p":{"a":0,"k":[0,0]},"s":{"a":0,"k":[100,100]},"sk":{"a":0,"k":0},"sa":{"a":0,"k":0},"r":{"a":0,"k":0},"o":{"a":0,"k":100}}]},{"ty":"gr","nm":"Group","hd":false,"np":3,"it":[{"ty":"rc","nm":"Rectangle","hd":false,"p":{"a":0,"k":[2.75,2.75]},"s":{"a":0,"k":[11,11]},"r":{"a":0,"k":0}},{"ty":"fl","o":{"a":0,"k":0},"c":{"a":0,"k":[0,1,0,1]},"nm":"Fill","hd":false,"r":1},{"ty":"tr","a":{"a":0,"k":[0,0]},"p":{"a":0,"k":[0,0]},"s":{"a":0,"k":[100,100]},"sk":{"a":0,"k":0},"sa":{"a":0,"k":0},"r":{"a":0,"k":0},"o":{"a":0,"k":100}}]}]}]}],"layers":[{"ty":3,"ddd":0,"ind":5,"hd":false,"nm":"manual-gearbox 1 - Null","ks":{"a":{"a":0,"k":[0,0]},"o":{"a":0,"k":100},"p":{"a":0,"k":[0,0]},"r":{"a":0,"k":0},"s":{"a":0,"k":[100,100]},"sk":{"a":0,"k":0},"sa":{"a":0,"k":0}},"st":0,"ip":0,"op":60,"bm":0,"sr":1},{"ddd":0,"ind":2,"ty":0,"nm":"manual-gearbox 1","refId":"ln4w6oez2e39o1sczo4","sr":1,"ks":{"a":{"a":0,"k":[0,0]},"p":{"a":0,"k":[0,0]},"s":{"a":0,"k":[100,100]},"sk":{"a":0,"k":0},"sa":{"a":0,"k":0},"r":{"a":0,"k":0},"o":{"a":0,"k":100}},"ao":0,"w":24,"h":24,"ip":0,"op":60,"st":0,"hd":false,"bm":0}],"meta":{"a":"","d":"","tc":"","g":"Aninix"}}